openmc_mesh_tally_to_vtk/__init__.py
openmc_mesh_tally_to_vtk/core.py
openmc_mesh_tally_to_vtk/utils.py
openmc_mesh_tally_to_vtk-0.2.1.dist-info/LICENSE
openmc_mesh_tally_to_vtk-0.2.1.dist-info/METADATA
openmc_mesh_tally_to_vtk-0.2.1.dist-info/WHEEL
openmc_mesh_tally_to_vtk-0.2.1.dist-info/top_level.txt
openmc_mesh_tally_to_vtk-0.2.1.dist-info/RECORD
