Metadata-Version: 2.1
Name: openmc-mesh-tally-to-vtk
Version: 0.2.1
Summary: A Python package for converting OpenMC mesh tallies to VTK files and optionally converting the units
Home-page: https://github.com/fusion-energy/openmc_mesh_tally_to_vtk
Author: The Regular Mesh Plotter Development Team
Author-email: mail@jshimwell.com
License: UNKNOWN
Platform: UNKNOWN
Classifier: Natural Language :: English
Classifier: Topic :: Scientific/Engineering
Classifier: Programming Language :: Python :: 3
Classifier: Programming Language :: Python :: 3.6
Classifier: Programming Language :: Python :: 3.7
Classifier: Programming Language :: Python :: 3.8
Classifier: Programming Language :: Python :: 3.9
Classifier: License :: OSI Approved :: MIT License
Classifier: Operating System :: OS Independent
Requires-Python: >=3.6
License-File: LICENSE
Requires-Dist: numpy (>=1.21.1)
Requires-Dist: matplotlib (>=3.4.2)
Requires-Dist: trimesh
Requires-Dist: shapely
Requires-Dist: scipy
Requires-Dist: dagmc-geometry-slice-plotter
Requires-Dist: openmc-tally-unit-converter
Requires-Dist: vtk
